django_smartstaticfiles/__init__.py
django_smartstaticfiles/settings.py
django_smartstaticfiles/storage.py
django_smartstaticfiles-0.3.2.dist-info/DESCRIPTION.rst
django_smartstaticfiles-0.3.2.dist-info/METADATA
django_smartstaticfiles-0.3.2.dist-info/RECORD
django_smartstaticfiles-0.3.2.dist-info/WHEEL
django_smartstaticfiles-0.3.2.dist-info/metadata.json
django_smartstaticfiles-0.3.2.dist-info/top_level.txt
