Metadata-Version: 2.0
Name: django-smartstaticfiles
Version: 0.3.2
Summary: Provides enhanced static files storage backend for Django 1.11
Home-page: https://github.com/rockallite/django-smartstaticfiles
Author: Rockallite Wulf
Author-email: rockallite.wulf@gmail.com
License: BSD License
Platform: UNKNOWN
Classifier: Development Status :: 3 - Alpha
Classifier: Environment :: Web Environment
Classifier: Framework :: Django
Classifier: Framework :: Django :: 1.11
Classifier: Intended Audience :: Developers
Classifier: License :: OSI Approved :: BSD License
Classifier: Operating System :: OS Independent
Classifier: Programming Language :: Python
Classifier: Programming Language :: Python :: 2
Classifier: Programming Language :: Python :: 2.7
Classifier: Programming Language :: Python :: 3
Classifier: Programming Language :: Python :: 3.4
Classifier: Programming Language :: Python :: 3.5
Classifier: Programming Language :: Python :: 3.6
Classifier: Topic :: Internet :: WWW/HTTP
Classifier: Topic :: Internet :: WWW/HTTP :: Dynamic Content
Classifier: Topic :: Software Development :: Libraries :: Python Modules
Requires-Dist: Django (<1.12,>=1.11)
Provides-Extra: cssmin
Requires-Dist: rcssmin; extra == 'cssmin'
Provides-Extra: jsmin
Requires-Dist: rjsmin; extra == 'jsmin'
